quhep/__init__.py
quhep/qsk_circ/QuantumCircuit.py
quhep/qsk_circ/QuantumFlow.py
quhep/qsk_circ/__init__.py
quhep/qsk_prop/HybridFunction.py
quhep/qsk_prop/__init__.py
quhep/tfq_net/ClassicalNN.py
quhep/tfq_net/QConvNN.py
quhep/tfq_net/QConvNNHYB.py
quhep/tfq_net/QDensNN.py
quhep/tfq_net/QEfficientSU2NNHYB.py
quhep/tfq_net/QEfficientSU2NNHYB2.py
quhep/tfq_net/QEfficientSU2NNQNN.py
quhep/tfq_net/QMNISTNN.py
quhep/tfq_net/QZinnerCNOTNN.py
quhep/tfq_net/QZinnerCNOTNNHYB.py
quhep/tfq_net/__init__.py
quhep/train/__init__.py
quhep/train/train.py
quhep/train/train_qsk.py
quhep/train/train_tfq.py
quhep/util/__init__.py
quhep/util/averageROC.py
quhep/util/extracAUC.py
quhep/util/inspecPQC.py
quhep-0.0.3.dist-info/METADATA
quhep-0.0.3.dist-info/WHEEL
quhep-0.0.3.dist-info/entry_points.txt
quhep-0.0.3.dist-info/top_level.txt
quhep-0.0.3.dist-info/RECORD
