Metadata-Version: 2.1
Name: quhep
Version: 0.0.3
Summary: Quantum Machine Learning Framework for High Energy Physics
Home-page: https://github.com/chnzhangrui/quhep
Author: Rui Zhang
Author-email: rui.zhang@cern.ch
License: MIT
Download-URL: https://pypi.org/project/quhep/
Keywords: Quantum Machine Learning,Tensorflow Quantum,Qiskit pyTorch
Platform: UNKNOWN
